[
    {
        "genre": "Comedy, Drama, Romance",
        "imdb_key": "tt1022603",
        "name": "(500) Days of Summer",
        "year": "2009",
        "script_url": "http://www.imsdb.com/scripts/500-Days-of-Summer.html",
        "imdb_url": "http://www.imdb.com/title/tt1022603"
    },
    {
        "genre": "Comedy, Drama, Romance",
        "imdb_key": "tt0147800",
        "name": "10 Things I Hate About You",
        "year": "1999",
        "script_url": "http://www.imsdb.com/scripts/10-Things-I-Hate-About-You.html",
        "imdb_url": "http://www.imdb.com/title/tt0147800"
    },
    {
        "genre": "Biography, Drama, History",
        "imdb_key": "tt2024544",
        "name": "12 Years a Slave",
        "year": "2013",
        "script_url": "http://www.imsdb.com/scripts/12-Years-a-Slave.html",
        "imdb_url": "http://www.imdb.com/title/tt2024544"
    },
    {
        "genre": "Action, Adventure, Sci-Fi",
        "imdb_key": "tt1190080",
        "name": "2012",
        "year": "2009",
        "script_url": "http://www.imsdb.com/scripts/2012.html",
        "imdb_url": "http://www.imdb.com/title/tt1190080"
    },
    {
        "genre": "Drama, Thriller",
        "imdb_key": "tt0104257",
        "name": "A Few Good Men",
        "year": "1992",
        "script_url": "http://www.imsdb.com/scripts/A-Few-Good-Men.html",
        "imdb_url": "http://www.imdb.com/title/tt0104257"
    },
    {
        "genre": "Drama, Romance",
        "imdb_key": "tt0281358",
        "name": "A Walk to Remember",
        "year": "2002",
        "script_url": "http://www.imsdb.com/scripts/Walk-to-Remember,-A.html",
        "imdb_url": "http://www.imdb.com/title/tt0281358"
    },
    {
        "genre": "Drama, Mystery, Thriller",
        "imdb_key": "tt0118564",
        "name": "Affliction",
        "year": "1997",
        "script_url": "http://www.imsdb.com/scripts/Affliction.html",
        "imdb_url": "http://www.imdb.com/title/tt0118564"
    },
    {
        "genre": "Action, Adventure, Drama, Thriller",
        "imdb_key": "tt0118571",
        "name": "Air Force One",
        "year": "1997",
        "script_url": "http://www.imsdb.com/scripts/Air-Force-One.html",
        "imdb_url": "http://www.imdb.com/title/tt0118571"
    },
    {
        "genre": "Drama, Music, Romance",
        "imdb_key": "tt0181875",
        "name": "Almost Famous",
        "year": "2000",
        "script_url": "http://www.imsdb.com/scripts/Almost-Famous.html",
        "imdb_url": "http://www.imdb.com/title/tt0181875"
    },
    {
        "genre": "Biography, Drama, Music",
        "imdb_key": "tt0086879",
        "name": "Amadeus",
        "year": "1984",
        "script_url": "http://www.imsdb.com/scripts/Amadeus.html",
        "imdb_url": "http://www.imdb.com/title/tt0086879"
    },
    {
        "genre": "Drama, Romance",
        "imdb_key": "tt0169547",
        "name": "American Beauty",
        "year": "1999",
        "script_url": "http://www.imsdb.com/scripts/American-Beauty.html",
        "imdb_url": "http://www.imdb.com/title/tt0169547"
    },
    {
        "genre": "Biography, Crime, Drama",
        "imdb_key": "tt0765429",
        "name": "American Gangster",
        "year": "2007",
        "script_url": "http://www.imsdb.com/scripts/American-Gangster.html",
        "imdb_url": "http://www.imdb.com/title/tt0765429"
    },
    {
        "genre": "Crime, Drama",
        "imdb_key": "tt0120586",
        "name": "American History X",
        "year": "1998",
        "script_url": "http://www.imsdb.com/scripts/American-History-X.html",
        "imdb_url": "http://www.imdb.com/title/tt0120586"
    },
    {
        "genre": "Crime, Drama",
        "imdb_key": "tt1800241",
        "name": "American Hustle",
        "year": "2013",
        "script_url": "http://www.imsdb.com/scripts/American-Hustle.html",
        "imdb_url": "http://www.imdb.com/title/tt1800241"
    },
    {
        "genre": "Drama, Horror",
        "imdb_key": "tt0144084",
        "name": "American Psycho",
        "year": "2000",
        "script_url": "http://www.imsdb.com/scripts/American-Psycho.html",
        "imdb_url": "http://www.imdb.com/title/tt0144084"
    },
    {
        "genre": "Drama",
        "imdb_key": "tt1174732",
        "name": "An Education",
        "year": "2009",
        "script_url": "http://www.imsdb.com/scripts/An-Education.html",
        "imdb_url": "http://www.imdb.com/title/tt1174732"
    },
    {
        "genre": "Animation, Adventure, Drama, Family, Fantasy, Musical, Mystery, Romance",
        "imdb_key": "tt0118617",
        "name": "Anastasia",
        "year": "1997",
        "script_url": "http://www.imsdb.com/scripts/Anastasia.html",
        "imdb_url": "http://www.imdb.com/title/tt0118617"
    },
    {
        "genre": "Drama, Romance",
        "imdb_key": "tt1781769",
        "name": "Anna Karenina",
        "year": "2012",
        "script_url": "http://www.imsdb.com/scripts/Anna-Karenina.html",
        "imdb_url": "http://www.imdb.com/title/tt1781769"
    },
    {
        "genre": "Drama, History, Thriller",
        "imdb_key": "tt1024648",
        "name": "Argo",
        "year": "2012",
        "script_url": "http://www.imsdb.com/scripts/Argo.html",
        "imdb_url": "http://www.imdb.com/title/tt1024648"
    },
    {
        "genre": "Comedy, Drama, Romance",
        "imdb_key": "tt0119822",
        "name": "As Good as It Gets",
        "year": "1997",
        "script_url": "http://www.imsdb.com/scripts/As-Good-As-It-Gets.html",
        "imdb_url": "http://www.imdb.com/title/tt0119822"
    },
    {
        "genre": "Action, Adventure, Fantasy, Sci-Fi",
        "imdb_key": "tt0499549",
        "name": "Avatar",
        "year": "2009",
        "script_url": "http://www.imsdb.com/scripts/Avatar.html",
        "imdb_url": "http://www.imdb.com/title/tt0499549"
    },
    {
        "genre": "Action, Crime, Drama, Mystery, Thriller",
        "imdb_key": "tt0101393",
        "name": "Backdraft",
        "year": "1991",
        "script_url": "http://www.imsdb.com/scripts/Backdraft.html",
        "imdb_url": "http://www.imdb.com/title/tt0101393"
    },
    {
        "genre": "Comedy, Crime, Drama",
        "imdb_key": "tt0307987",
        "name": "Bad Santa",
        "year": "2003",
        "script_url": "http://www.imsdb.com/scripts/Bad-Santa.html",
        "imdb_url": "http://www.imdb.com/title/tt0307987"
    },
    {
        "genre": "Comedy",
        "imdb_key": "tt1284575",
        "name": "Bad Teacher",
        "year": "2011",
        "script_url": "http://www.imsdb.com/scripts/Bad-Teacher.html",
        "imdb_url": "http://www.imdb.com/title/tt1284575"
    },
    {
        "genre": "Action, Adventure",
        "imdb_key": "tt0096895",
        "name": "Batman",
        "year": "1989",
        "script_url": "http://www.imsdb.com/scripts/Batman.html",
        "imdb_url": "http://www.imdb.com/title/tt0096895"
    },
    {
        "genre": "Adventure, Drama, Fantasy",
        "imdb_key": "tt0319061",
        "name": "Big Fish",
        "year": "2003",
        "script_url": "http://www.imsdb.com/scripts/Big-Fish.html",
        "imdb_url": "http://www.imdb.com/title/tt0319061"
    },
    {
        "genre": "Drama, Thriller",
        "imdb_key": "tt0947798",
        "name": "Black Swan",
        "year": "2010",
        "script_url": "http://www.imsdb.com/scripts/Black-Swan.html",
        "imdb_url": "http://www.imdb.com/title/tt0947798"
    },
    {
        "genre": "Action, Horror",
        "imdb_key": "tt0120611",
        "name": "Blade",
        "year": "1998",
        "script_url": "http://www.imsdb.com/scripts/Blade.html",
        "imdb_url": "http://www.imdb.com/title/tt0120611"
    },
    {
        "genre": "Sci-Fi, Thriller",
        "imdb_key": "tt0083658",
        "name": "Blade Runner",
        "year": "1982",
        "script_url": "http://www.imsdb.com/scripts/Blade-Runner.html",
        "imdb_url": "http://www.imdb.com/title/tt0083658"
    },
    {
        "genre": "Biography, Crime, Drama",
        "imdb_key": "tt0221027",
        "name": "Blow",
        "year": "2001",
        "script_url": "http://www.imsdb.com/scripts/Blow.html",
        "imdb_url": "http://www.imdb.com/title/tt0221027"
    },
    {
        "genre": "Drama, Romance",
        "imdb_key": "tt1120985",
        "name": "Blue Valentine",
        "year": "2010",
        "script_url": "http://www.imsdb.com/scripts/Blue-Valentine.html",
        "imdb_url": "http://www.imdb.com/title/tt1120985"
    },
    {
        "genre": "Crime, Drama, Mystery, Thriller",
        "imdb_key": "tt0090756",
        "name": "Blue Velvet",
        "year": "1986",
        "script_url": "http://www.imsdb.com/scripts/Blue-Velvet.html",
        "imdb_url": "http://www.imdb.com/title/tt0090756"
    },
    {
        "genre": "Biography, Drama, History, War",
        "imdb_key": "tt0112573",
        "name": "Braveheart",
        "year": "1995",
        "script_url": "http://www.imsdb.com/scripts/Braveheart.html",
        "imdb_url": "http://www.imdb.com/title/tt0112573"
    },
    {
        "genre": "Comedy, Romance",
        "imdb_key": "tt1478338",
        "name": "Bridesmaids",
        "year": "2011",
        "script_url": "http://www.imsdb.com/scripts/Bridesmaids.html",
        "imdb_url": "http://www.imdb.com/title/tt1478338"
    },
    {
        "genre": "Comedy, Drama, Fantasy",
        "imdb_key": "tt0315327",
        "name": "Bruce Almighty",
        "year": "2003",
        "script_url": "http://www.imsdb.com/scripts/Bruce-Almighty.html",
        "imdb_url": "http://www.imdb.com/title/tt0315327"
    },
    {
        "genre": "Comedy, Crime, Drama",
        "imdb_key": "tt0887883",
        "name": "Burn After Reading",
        "year": "2008",
        "script_url": "http://www.imsdb.com/scripts/Burn-After-Reading.html",
        "imdb_url": "http://www.imdb.com/title/tt0887883"
    },
    {
        "genre": "Horror",
        "imdb_key": "tt0074285",
        "name": "Carrie",
        "year": "1976",
        "script_url": "http://www.imsdb.com/scripts/Carrie.html",
        "imdb_url": "http://www.imdb.com/title/tt0074285"
    },
    {
        "genre": "Comedy, Mystery, Romance, Thriller",
        "imdb_key": "tt0056923",
        "name": "Charade",
        "year": "1963",
        "script_url": "http://www.imsdb.com/scripts/Charade.html",
        "imdb_url": "http://www.imdb.com/title/tt0056923"
    },
    {
        "genre": "Comedy, Drama, Romance",
        "imdb_key": "tt0118842",
        "name": "Chasing Amy",
        "year": "1997",
        "script_url": "http://www.imsdb.com/scripts/Chasing-Amy.html",
        "imdb_url": "http://www.imdb.com/title/tt0118842"
    },
    {
        "genre": "Drama, Mystery, Thriller",
        "imdb_key": "tt0071315",
        "name": "Chinatown",
        "year": "1974",
        "script_url": "http://www.imsdb.com/scripts/Chinatown.html",
        "imdb_url": "http://www.imdb.com/title/tt0071315"
    },
    {
        "genre": "Drama, Sci-Fi, Thriller",
        "imdb_key": "tt1706593",
        "name": "Chronicle",
        "year": "2012",
        "script_url": "http://www.imsdb.com/scripts/Chronicle.html",
        "imdb_url": "http://www.imdb.com/title/tt1706593"
    },
    {
        "genre": "Action, Adventure, Fantasy",
        "imdb_key": "tt0800320",
        "name": "Clash of the Titans",
        "year": "2010",
        "script_url": "http://www.imsdb.com/scripts/Clash-of-the-Titans.html",
        "imdb_url": "http://www.imdb.com/title/tt0800320"
    },
    {
        "genre": "Comedy",
        "imdb_key": "tt0109445",
        "name": "Clerks",
        "year": "1994",
        "script_url": "http://www.imsdb.com/scripts/Clerks.html",
        "imdb_url": "http://www.imdb.com/title/tt0109445"
    },
    {
        "genre": "Comedy, Romance",
        "imdb_key": "tt0112697",
        "name": "Clueless",
        "year": "1995",
        "script_url": "http://www.imsdb.com/scripts/Clueless.html",
        "imdb_url": "http://www.imdb.com/title/tt0112697"
    },
    {
        "genre": "Adventure, Fantasy",
        "imdb_key": "tt0082198",
        "name": "Conan the Barbarian",
        "year": "1982",
        "script_url": "http://www.imsdb.com/scripts/Conan-the-Barbarian.html",
        "imdb_url": "http://www.imdb.com/title/tt0082198"
    },
    {
        "genre": "Animation, Fantasy",
        "imdb_key": "tt0327597",
        "name": "Coraline",
        "year": "2009",
        "script_url": "http://www.imsdb.com/scripts/Coraline.html",
        "imdb_url": "http://www.imdb.com/title/tt0327597"
    },
    {
        "genre": "Action, Sci-Fi, Thriller, Western",
        "imdb_key": "tt0409847",
        "name": "Cowboys & Aliens",
        "year": "2011",
        "script_url": "http://www.imsdb.com/scripts/Cowboys-&-Aliens.html",
        "imdb_url": "http://www.imdb.com/title/tt0409847"
    },
    {
        "genre": "Comedy, Drama, Romance",
        "imdb_key": "tt1570728",
        "name": "Crazy, Stupid, Love.",
        "year": "2011",
        "script_url": "http://www.imsdb.com/scripts/Crazy,-Stupid,-Love.html",
        "imdb_url": "http://www.imdb.com/title/tt1570728"
    },
    {
        "genre": "Drama, Romance",
        "imdb_key": "tt0139134",
        "name": "Cruel Intentions",
        "year": "1999",
        "script_url": "http://www.imsdb.com/scripts/Cruel-Intentions.html",
        "imdb_url": "http://www.imdb.com/title/tt0139134"
    },
    {
        "genre": "Drama",
        "imdb_key": "tt0097165",
        "name": "Dead Poets Society",
        "year": "1989",
        "script_url": "http://www.imsdb.com/scripts/Dead-Poets-Society.html",
        "imdb_url": "http://www.imdb.com/title/tt0097165"
    },
    {
        "genre": "Drama, Mystery, Thriller",
        "imdb_key": "tt0486822",
        "name": "Disturbia",
        "year": "2007",
        "script_url": "http://www.imsdb.com/scripts/Disturbia.html",
        "imdb_url": "http://www.imdb.com/title/tt0486822"
    },
    {
        "genre": "Western",
        "imdb_key": "tt1853728",
        "name": "Django Unchained",
        "year": "2012",
        "script_url": "http://www.imsdb.com/scripts/Django-Unchained.html",
        "imdb_url": "http://www.imdb.com/title/tt1853728"
    },
    {
        "genre": "Crime, Drama, Film-Noir, Thriller",
        "imdb_key": "tt0036775",
        "name": "Double Indemnity",
        "year": "1944",
        "script_url": "http://www.imsdb.com/scripts/Double-Indemnity.html",
        "imdb_url": "http://www.imdb.com/title/tt0036775"
    },
    {
        "genre": "Crime, Drama",
        "imdb_key": "tt0780504",
        "name": "Drive",
        "year": "2011",
        "script_url": "http://www.imsdb.com/scripts/Drive.html",
        "imdb_url": "http://www.imdb.com/title/tt0780504"
    },
    {
        "genre": "Family, Sci-Fi",
        "imdb_key": "tt0083866",
        "name": "E.T. the Extra-Terrestrial",
        "year": "1982",
        "script_url": "http://www.imsdb.com/scripts/E.T..html",
        "imdb_url": "http://www.imdb.com/title/tt0083866"
    },
    {
        "genre": "Drama, Fantasy, Romance",
        "imdb_key": "tt0099487",
        "name": "Edward Scissorhands",
        "year": "1990",
        "script_url": "http://www.imsdb.com/scripts/Edward-Scissorhands.html",
        "imdb_url": "http://www.imdb.com/title/tt0099487"
    },
    {
        "genre": "Horror, Sci-Fi",
        "imdb_key": "tt0119081",
        "name": "Event Horizon",
        "year": "1997",
        "script_url": "http://www.imsdb.com/scripts/Event-Horizon.html",
        "imdb_url": "http://www.imdb.com/title/tt0119081"
    },
    {
        "genre": "Comedy",
        "imdb_key": "tt0091042",
        "name": "Ferris Bueller's Day Off",
        "year": "1986",
        "script_url": "http://www.imsdb.com/scripts/Ferris-Bueller's-Day-Off.html",
        "imdb_url": "http://www.imdb.com/title/tt0091042"
    },
    {
        "genre": "Drama",
        "imdb_key": "tt0137523",
        "name": "Fight Club",
        "year": "1999",
        "script_url": "http://www.imsdb.com/scripts/Fight-Club.html",
        "imdb_url": "http://www.imdb.com/title/tt0137523"
    },
    {
        "genre": "Drama, Thriller",
        "imdb_key": "tt1907668",
        "name": "Flight",
        "year": "2012",
        "script_url": "http://www.imsdb.com/scripts/Flight.html",
        "imdb_url": "http://www.imdb.com/title/tt1907668"
    },
    {
        "genre": "Drama, Romance",
        "imdb_key": "tt0109830",
        "name": "Forrest Gump",
        "year": "1994",
        "script_url": "http://www.imsdb.com/scripts/Forrest-Gump.html",
        "imdb_url": "http://www.imdb.com/title/tt0109830"
    },
    {
        "genre": "Animation, Adventure, Comedy, Family, Fantasy, Musical",
        "imdb_key": "tt2294629",
        "name": "Frozen",
        "year": "2013",
        "script_url": "http://www.imsdb.com/scripts/Frozen.html",
        "imdb_url": "http://www.imdb.com/title/tt2294629"
    },
    {
        "genre": "Action, Adventure, Sci-Fi, Thriller",
        "imdb_key": "tt1046173",
        "name": "G.I. Joe: The Rise of Cobra",
        "year": "2009",
        "script_url": "http://www.imsdb.com/scripts/G.I.-Joe-The-Rise-of-Cobra.html",
        "imdb_url": "http://www.imdb.com/title/tt1046173"
    },
    {
        "genre": "Biography, Drama, History",
        "imdb_key": "tt0083987",
        "name": "Gandhi",
        "year": "1982",
        "script_url": "http://www.imsdb.com/scripts/Gandhi.html",
        "imdb_url": "http://www.imdb.com/title/tt0083987"
    },
    {
        "genre": "Drama, Fantasy, Romance, Thriller",
        "imdb_key": "tt0099653",
        "name": "Ghost",
        "year": "1990",
        "script_url": "http://www.imsdb.com/scripts/Ghost.html",
        "imdb_url": "http://www.imdb.com/title/tt0099653"
    },
    {
        "genre": "Action, Drama",
        "imdb_key": "tt0172495",
        "name": "Gladiator",
        "year": "2000",
        "script_url": "http://www.imsdb.com/scripts/Gladiator.html",
        "imdb_url": "http://www.imdb.com/title/tt0172495"
    },
    {
        "genre": "Biography, Drama",
        "imdb_key": "tt0120684",
        "name": "Gods and Monsters",
        "year": "1998",
        "script_url": "http://www.imsdb.com/scripts/Gods-and-Monsters.html",
        "imdb_url": "http://www.imdb.com/title/tt0120684"
    },
    {
        "genre": "Drama",
        "imdb_key": "tt1205489",
        "name": "Gran Torino",
        "year": "2008",
        "script_url": "http://www.imsdb.com/scripts/Gran-Torino.html",
        "imdb_url": "http://www.imdb.com/title/tt1205489"
    },
    {
        "genre": "Sci-Fi, Thriller",
        "imdb_key": "tt1454468",
        "name": "Gravity",
        "year": "2013",
        "script_url": "http://www.imsdb.com/scripts/Gravity.html",
        "imdb_url": "http://www.imdb.com/title/tt1454468"
    },
    {
        "genre": "Comedy, Romance",
        "imdb_key": "tt0107048",
        "name": "Groundhog Day",
        "year": "1993",
        "script_url": "http://www.imsdb.com/scripts/Groundhog-Day.html",
        "imdb_url": "http://www.imdb.com/title/tt0107048"
    },
    {
        "genre": "Comedy, Crime, Drama, Thriller",
        "imdb_key": "tt0113243",
        "name": "Hackers",
        "year": "1995",
        "script_url": "http://www.imsdb.com/scripts/Hackers.html",
        "imdb_url": "http://www.imdb.com/title/tt0113243"
    },
    {
        "genre": "Comedy, Drama, Romance",
        "imdb_key": "tt1001508",
        "name": "He's Just Not That Into You",
        "year": "2009",
        "script_url": "http://www.imsdb.com/scripts/He's-Just-Not-That-Into-You.html",
        "imdb_url": "http://www.imdb.com/title/tt1001508"
    },
    {
        "genre": "Comedy, Drama, Music, Romance",
        "imdb_key": "tt0146882",
        "name": "High Fidelity",
        "year": "2000",
        "script_url": "http://www.imsdb.com/scripts/High-Fidelity.html",
        "imdb_url": "http://www.imdb.com/title/tt0146882"
    },
    {
        "genre": "Comedy, Crime",
        "imdb_key": "tt1499658",
        "name": "Horrible Bosses",
        "year": "2011",
        "script_url": "http://www.imsdb.com/scripts/Horrible-Bosses.html",
        "imdb_url": "http://www.imdb.com/title/tt1499658"
    },
    {
        "genre": "Animation, Action, Adventure, Comedy, Family, Fantasy",
        "imdb_key": "tt1646971",
        "name": "How to Train Your Dragon 2",
        "year": "2014",
        "script_url": "http://www.imsdb.com/scripts/How-to-Train-Your-Dragon-2.html",
        "imdb_url": "http://www.imdb.com/title/tt1646971"
    },
    {
        "genre": "Action, Mystery, Sci-Fi, Thriller",
        "imdb_key": "tt0343818",
        "name": "I, Robot",
        "year": "2004",
        "script_url": "http://www.imsdb.com/scripts/I,-Robot.html",
        "imdb_url": "http://www.imdb.com/title/tt0343818"
    },
    {
        "genre": "Action, Mystery, Romance, Sci-Fi, Thriller",
        "imdb_key": "tt1375666",
        "name": "Inception",
        "year": "2010",
        "script_url": "http://www.imsdb.com/scripts/Inception.html",
        "imdb_url": "http://www.imdb.com/title/tt1375666"
    },
    {
        "genre": "Action, Adventure, Sci-Fi",
        "imdb_key": "tt0116629",
        "name": "Independence Day",
        "year": "1996",
        "script_url": "http://www.imsdb.com/scripts/Independence-Day.html",
        "imdb_url": "http://www.imdb.com/title/tt0116629"
    },
    {
        "genre": "Action, Adventure",
        "imdb_key": "tt0097576",
        "name": "Indiana Jones and the Last Crusade",
        "year": "1989",
        "script_url": "http://www.imsdb.com/scripts/Indiana-Jones-and-the-Last-Crusade.html",
        "imdb_url": "http://www.imdb.com/title/tt0097576"
    },
    {
        "genre": "Action, Adventure",
        "imdb_key": "tt0087469",
        "name": "Indiana Jones and the Temple of Doom",
        "year": "1984",
        "script_url": "http://www.imsdb.com/scripts/Indiana-Jones-and-the-Temple-of-Doom.html",
        "imdb_url": "http://www.imdb.com/title/tt0087469"
    },
    {
        "genre": "Crime, Drama, Thriller",
        "imdb_key": "tt0119396",
        "name": "Jackie Brown",
        "year": "1997",
        "script_url": "http://www.imsdb.com/scripts/Jackie-Brown.html",
        "imdb_url": "http://www.imdb.com/title/tt0119396"
    },
    {
        "genre": "Drama, Romance",
        "imdb_key": "tt1229822",
        "name": "Jane Eyre",
        "year": "2011",
        "script_url": "http://www.imsdb.com/scripts/Jane-Eyre.html",
        "imdb_url": "http://www.imdb.com/title/tt1229822"
    },
    {
        "genre": "Comedy, Horror",
        "imdb_key": "tt1131734",
        "name": "Jennifer's Body",
        "year": "2009",
        "script_url": "http://www.imsdb.com/scripts/Jennifer's-Body.html",
        "imdb_url": "http://www.imdb.com/title/tt1131734"
    },
    {
        "genre": "Comedy, Drama, Romance",
        "imdb_key": "tt0467406",
        "name": "Juno",
        "year": "2007",
        "script_url": "http://www.imsdb.com/scripts/Juno.html",
        "imdb_url": "http://www.imdb.com/title/tt0467406"
    },
    {
        "genre": "Adventure, Sci-Fi, Thriller",
        "imdb_key": "tt0107290",
        "name": "Jurassic Park",
        "year": "1993",
        "script_url": "http://www.imsdb.com/scripts/Jurassic-Park.html",
        "imdb_url": "http://www.imdb.com/title/tt0107290"
    },
    {
        "genre": "Action, Adventure, Sci-Fi, Thriller",
        "imdb_key": "tt0163025",
        "name": "Jurassic Park III",
        "year": "2001",
        "script_url": "http://www.imsdb.com/scripts/Jurassic-Park-III.html",
        "imdb_url": "http://www.imdb.com/title/tt0163025"
    },
    {
        "genre": "Comedy, Drama, Romance",
        "imdb_key": "tt0478311",
        "name": "Knocked Up",
        "year": "2007",
        "script_url": "http://www.imsdb.com/scripts/Knocked-Up.html",
        "imdb_url": "http://www.imdb.com/title/tt0478311"
    },
    {
        "genre": "Animation, Action, Adventure, Comedy, Family",
        "imdb_key": "tt0441773",
        "name": "Kung Fu Panda",
        "year": "2008",
        "script_url": "http://www.imsdb.com/scripts/Kung-Fu-Panda.html",
        "imdb_url": "http://www.imdb.com/title/tt0441773"
    },
    {
        "genre": "Crime, Drama, Mystery, Thriller",
        "imdb_key": "tt0119488",
        "name": "L.A. Confidential",
        "year": "1997",
        "script_url": "http://www.imsdb.com/scripts/L.A.-Confidential.html",
        "imdb_url": "http://www.imdb.com/title/tt0119488"
    },
    {
        "genre": "Crime, Drama, Thriller",
        "imdb_key": "tt1197624",
        "name": "Law Abiding Citizen",
        "year": "2009",
        "script_url": "http://www.imsdb.com/scripts/Law-Abiding-Citizen.html",
        "imdb_url": "http://www.imdb.com/title/tt1197624"
    },
    {
        "genre": "Drama, Musical, Romance",
        "imdb_key": "tt1707386",
        "name": "Les Miserables",
        "year": "2012",
        "script_url": "http://www.imsdb.com/scripts/Les-Miserables.html",
        "imdb_url": "http://www.imdb.com/title/tt1707386"
    },
    {
        "genre": "Comedy, Crime",
        "imdb_key": "tt0120735",
        "name": "Lock, Stock and Two Smoking Barrels",
        "year": "1998",
        "script_url": "http://www.imsdb.com/scripts/Lock,-Stock-and-Two-Smoking-Barrels.html",
        "imdb_url": "http://www.imdb.com/title/tt0120735"
    },
    {
        "genre": "Action, Crime, Sci-Fi, Thriller",
        "imdb_key": "tt1276104",
        "name": "Looper",
        "year": "2012",
        "script_url": "http://www.imsdb.com/scripts/Looper.html",
        "imdb_url": "http://www.imdb.com/title/tt1276104"
    },
    {
        "genre": "Drama",
        "imdb_key": "tt0335266",
        "name": "Lost in Translation",
        "year": "2003",
        "script_url": "http://www.imsdb.com/scripts/Lost-in-Translation.html",
        "imdb_url": "http://www.imdb.com/title/tt0335266"
    },
    {
        "genre": "Action, Crime, Drama, Thriller",
        "imdb_key": "tt0328107",
        "name": "Man on Fire",
        "year": "2004",
        "script_url": "http://www.imsdb.com/scripts/Man-On-Fire.html",
        "imdb_url": "http://www.imdb.com/title/tt0328107"
    },
    {
        "genre": "Drama, Thriller",
        "imdb_key": "tt1615147",
        "name": "Margin Call",
        "year": "2011",
        "script_url": "http://www.imsdb.com/scripts/Margin-Call.html",
        "imdb_url": "http://www.imdb.com/title/tt1615147"
    },
    {
        "genre": "Comedy, Drama, Family, Romance",
        "imdb_key": "tt0822832",
        "name": "Marley & Me",
        "year": "2008",
        "script_url": "http://www.imsdb.com/scripts/Marley-&-Me.html",
        "imdb_url": "http://www.imdb.com/title/tt0822832"
    },
    {
        "genre": "Drama, Fantasy, Romance",
        "imdb_key": "tt0119643",
        "name": "Meet Joe Black",
        "year": "1998",
        "script_url": "http://www.imsdb.com/scripts/Meet-Joe-Black.html",
        "imdb_url": "http://www.imdb.com/title/tt0119643"
    },
    {
        "genre": "Comedy, Sci-Fi",
        "imdb_key": "tt0119654",
        "name": "Men in Black",
        "year": "1997",
        "script_url": "http://www.imsdb.com/scripts/Men-in-Black.html",
        "imdb_url": "http://www.imdb.com/title/tt0119654"
    },
    {
        "genre": "Action, Comedy, Sci-Fi",
        "imdb_key": "tt1409024",
        "name": "Men in Black 3",
        "year": "2012",
        "script_url": "http://www.imsdb.com/scripts/Men-in-Black-3.html",
        "imdb_url": "http://www.imdb.com/title/tt1409024"
    },
    {
        "genre": "Comedy, Romance",
        "imdb_key": "tt1605783",
        "name": "Midnight in Paris",
        "year": "2011",
        "script_url": "http://www.imsdb.com/scripts/Midnight-in-Paris.html",
        "imdb_url": "http://www.imdb.com/title/tt1605783"
    },
    {
        "genre": "Biography, Drama, History",
        "imdb_key": "tt1013753",
        "name": "Milk",
        "year": "2008",
        "script_url": "http://www.imsdb.com/scripts/Milk.html",
        "imdb_url": "http://www.imdb.com/title/tt1013753"
    },
    {
        "genre": "Drama, Sci-Fi",
        "imdb_key": "tt1182345",
        "name": "Moon",
        "year": "2009",
        "script_url": "http://www.imsdb.com/scripts/Moon.html",
        "imdb_url": "http://www.imdb.com/title/tt1182345"
    },
    {
        "genre": "Adventure, Comedy, Drama, Romance",
        "imdb_key": "tt1748122",
        "name": "Moonrise Kingdom",
        "year": "2012",
        "script_url": "http://www.imsdb.com/scripts/Moonrise-Kingdom.html",
        "imdb_url": "http://www.imdb.com/title/tt1748122"
    },
    {
        "genre": "Crime, Drama, Mystery, Thriller",
        "imdb_key": "tt0780571",
        "name": "Mr. Brooks",
        "year": "2007",
        "script_url": "http://www.imsdb.com/scripts/Mr-Brooks.html",
        "imdb_url": "http://www.imdb.com/title/tt0780571"
    },
    {
        "genre": "Animation, Adventure, Family, Musical, War",
        "imdb_key": "tt0120762",
        "name": "Mulan",
        "year": "1998",
        "script_url": "http://www.imsdb.com/scripts/Mulan.html",
        "imdb_url": "http://www.imdb.com/title/tt0120762"
    },
    {
        "genre": "Drama, Mystery, Thriller",
        "imdb_key": "tt0166924",
        "name": "Mulholland Drive",
        "year": "2001",
        "script_url": "http://www.imsdb.com/scripts/Mulholland-Drive.html",
        "imdb_url": "http://www.imdb.com/title/tt0166924"
    },
    {
        "genre": "Action, Adventure, Mystery, Sci-Fi",
        "imdb_key": "tt1483013",
        "name": "Oblivion",
        "year": "2013",
        "script_url": "http://www.imsdb.com/scripts/Oblivion.html",
        "imdb_url": "http://www.imdb.com/title/tt1483013"
    },
    {
        "genre": "Crime, Thriller",
        "imdb_key": "tt0240772",
        "name": "Ocean's Eleven",
        "year": "2001",
        "script_url": "http://www.imsdb.com/scripts/Ocean's-Eleven.html",
        "imdb_url": "http://www.imdb.com/title/tt0240772"
    },
    {
        "genre": "Crime, Thriller",
        "imdb_key": "tt0349903",
        "name": "Ocean's Twelve",
        "year": "2004",
        "script_url": "http://www.imsdb.com/scripts/Ocean's-Twelve.html",
        "imdb_url": "http://www.imdb.com/title/tt0349903"
    },
    {
        "genre": "Comedy",
        "imdb_key": "tt0151804",
        "name": "Office Space",
        "year": "1999",
        "script_url": "http://www.imsdb.com/scripts/Office-Space.html",
        "imdb_url": "http://www.imdb.com/title/tt0151804"
    },
    {
        "genre": "Horror, Mystery, Thriller",
        "imdb_key": "tt1148204",
        "name": "Orphan",
        "year": "2009",
        "script_url": "http://www.imsdb.com/scripts/Orphan.html",
        "imdb_url": "http://www.imdb.com/title/tt1148204"
    },
    {
        "genre": "Adventure, Comedy, Sci-Fi",
        "imdb_key": "tt1092026",
        "name": "Paul",
        "year": "2011",
        "script_url": "http://www.imsdb.com/scripts/Paul.html",
        "imdb_url": "http://www.imdb.com/title/tt1092026"
    },
    {
        "genre": "Action, Drama, Romance, War",
        "imdb_key": "tt0213149",
        "name": "Pearl Harbor",
        "year": "2001",
        "script_url": "http://www.imsdb.com/scripts/Pearl-Harbor.html",
        "imdb_url": "http://www.imdb.com/title/tt0213149"
    },
    {
        "genre": "Action, Adventure, Fantasy",
        "imdb_key": "tt0383574",
        "name": "Pirates of the Caribbean: Dead Man's Chest",
        "year": "2006",
        "script_url": "http://www.imsdb.com/scripts/Pirates-of-the-Caribbean-Dead-Man's-Chest.html",
        "imdb_url": "http://www.imdb.com/title/tt0383574"
    },
    {
        "genre": "Action, Adventure, Fantasy",
        "imdb_key": "tt0325980",
        "name": "Pirates of the Caribbean: The Curse of the Black Pearl",
        "year": "2003",
        "script_url": "http://www.imsdb.com/scripts/Pirates-of-the-Caribbean.html",
        "imdb_url": "http://www.imdb.com/title/tt0325980"
    },
    {
        "genre": "Action, Adventure, Sci-Fi",
        "imdb_key": "tt0133152",
        "name": "Planet of the Apes",
        "year": "2001",
        "script_url": "http://www.imsdb.com/scripts/Planet-of-the-Apes,-The.html",
        "imdb_url": "http://www.imdb.com/title/tt0133152"
    },
    {
        "genre": "Comedy, Romance",
        "imdb_key": "tt0100405",
        "name": "Pretty Woman",
        "year": "1990",
        "script_url": "http://www.imsdb.com/scripts/Pretty-Woman.html",
        "imdb_url": "http://www.imdb.com/title/tt0100405"
    },
    {
        "genre": "Adventure, Mystery, Sci-Fi",
        "imdb_key": "tt1446714",
        "name": "Prometheus",
        "year": "2012",
        "script_url": "http://www.imsdb.com/scripts/Prometheus.html",
        "imdb_url": "http://www.imdb.com/title/tt1446714"
    },
    {
        "genre": "Crime, Drama",
        "imdb_key": "tt0110912",
        "name": "Pulp Fiction",
        "year": "1994",
        "script_url": "http://www.imsdb.com/scripts/Pulp-Fiction.html",
        "imdb_url": "http://www.imdb.com/title/tt0110912"
    },
    {
        "genre": "Action, Adventure",
        "imdb_key": "tt0082971",
        "name": "Raiders of the Lost Ark",
        "year": "1981",
        "script_url": "http://www.imsdb.com/scripts/Indiana-Jones-and-the-Raiders-of-the-Lost-Ark.html",
        "imdb_url": "http://www.imdb.com/title/tt0082971"
    },
    {
        "genre": "Drama, Romance",
        "imdb_key": "tt0959337",
        "name": "Revolutionary Road",
        "year": "2008",
        "script_url": "http://www.imsdb.com/scripts/Revolutionary-Road.html",
        "imdb_url": "http://www.imdb.com/title/tt0959337"
    },
    {
        "genre": "Action, Adventure, Drama, Romance",
        "imdb_key": "tt0102798",
        "name": "Robin Hood: Prince of Thieves",
        "year": "1991",
        "script_url": "http://www.imsdb.com/scripts/Robin-Hood-Prince-of-Thieves.html",
        "imdb_url": "http://www.imdb.com/title/tt0102798"
    },
    {
        "genre": "Action, Biography, Drama, Sport",
        "imdb_key": "tt1979320",
        "name": "Rush",
        "year": "2013",
        "script_url": "http://www.imsdb.com/scripts/Rush.html",
        "imdb_url": "http://www.imdb.com/title/tt1979320"
    },
    {
        "genre": "Action, Drama, War",
        "imdb_key": "tt0120815",
        "name": "Saving Private Ryan",
        "year": "1998",
        "script_url": "http://www.imsdb.com/scripts/Saving-Private-Ryan.html",
        "imdb_url": "http://www.imdb.com/title/tt0120815"
    },
    {
        "genre": "Biography, Drama, History",
        "imdb_key": "tt0108052",
        "name": "Schindler's List",
        "year": "1993",
        "script_url": "http://www.imsdb.com/scripts/Schindler's-List.html",
        "imdb_url": "http://www.imdb.com/title/tt0108052"
    },
    {
        "genre": "Action, Adventure, Sci-Fi, Thriller",
        "imdb_key": "tt0379786",
        "name": "Serenity",
        "year": "2005",
        "script_url": "http://www.imsdb.com/scripts/Serenity.html",
        "imdb_url": "http://www.imdb.com/title/tt0379786"
    },
    {
        "genre": "Comedy, Drama, Romance",
        "imdb_key": "tt1000774",
        "name": "Sex and the City",
        "year": "2008",
        "script_url": "http://www.imsdb.com/scripts/Sex-and-the-City.html",
        "imdb_url": "http://www.imdb.com/title/tt1000774"
    },
    {
        "genre": "Drama, Sci-Fi, Thriller",
        "imdb_key": "tt0286106",
        "name": "Signs",
        "year": "2002",
        "script_url": "http://www.imsdb.com/scripts/Signs.html",
        "imdb_url": "http://www.imdb.com/title/tt0286106"
    },
    {
        "genre": "Comedy, Drama, Romance",
        "imdb_key": "tt1045658",
        "name": "Silver Linings Playbook",
        "year": "2012",
        "script_url": "http://www.imsdb.com/scripts/Silver-Linings-Playbook.html",
        "imdb_url": "http://www.imdb.com/title/tt1045658"
    },
    {
        "genre": "Drama, Thriller",
        "imdb_key": "tt0105414",
        "name": "Single White Female",
        "year": "1992",
        "script_url": "http://www.imsdb.com/scripts/Single-White-Female.html",
        "imdb_url": "http://www.imdb.com/title/tt0105414"
    },
    {
        "genre": "Comedy, Drama, Romance",
        "imdb_key": "tt0108160",
        "name": "Sleepless in Seattle",
        "year": "1993",
        "script_url": "http://www.imsdb.com/scripts/Sleepless-in-Seattle.html",
        "imdb_url": "http://www.imdb.com/title/tt0108160"
    },
    {
        "genre": "Drama, Romance",
        "imdb_key": "tt1010048",
        "name": "Slumdog Millionaire",
        "year": "2008",
        "script_url": "http://www.imsdb.com/scripts/Slumdog-Millionaire.html",
        "imdb_url": "http://www.imdb.com/title/tt1010048"
    },
    {
        "genre": "Action, Crime, Drama, Thriller",
        "imdb_key": "tt0475394",
        "name": "Smokin' Aces",
        "year": "2006",
        "script_url": "http://www.imsdb.com/scripts/Smokin'-Aces.html",
        "imdb_url": "http://www.imdb.com/title/tt0475394"
    },
    {
        "genre": "Comedy, Crime",
        "imdb_key": "tt0208092",
        "name": "Snatch.",
        "year": "2000",
        "script_url": "http://www.imsdb.com/scripts/Snatch.html",
        "imdb_url": "http://www.imdb.com/title/tt0208092"
    },
    {
        "genre": "Action, Adventure, Fantasy, Sci-Fi",
        "imdb_key": "tt0076759",
        "name": "Star Wars",
        "year": "1977",
        "script_url": "http://www.imsdb.com/scripts/Star-Wars-A-New-Hope.html",
        "imdb_url": "http://www.imdb.com/title/tt0076759"
    },
    {
        "genre": "Action, Adventure, Fantasy, Sci-Fi",
        "imdb_key": "tt0120915",
        "name": "Star Wars: Episode I - The Phantom Menace",
        "year": "1999",
        "script_url": "http://www.imsdb.com/scripts/Star-Wars-The-Phantom-Menace.html",
        "imdb_url": "http://www.imdb.com/title/tt0120915"
    },
    {
        "genre": "Action, Adventure, Fantasy, Sci-Fi",
        "imdb_key": "tt0121765",
        "name": "Star Wars: Episode II - Attack of the Clones",
        "year": "2002",
        "script_url": "http://www.imsdb.com/scripts/Star-Wars-Attack-of-the-Clones.html",
        "imdb_url": "http://www.imdb.com/title/tt0121765"
    },
    {
        "genre": "Action, Adventure, Fantasy, Sci-Fi",
        "imdb_key": "tt0080684",
        "name": "Star Wars: Episode V - The Empire Strikes Back",
        "year": "1980",
        "script_url": "http://www.imsdb.com/scripts/Star-Wars-The-Empire-Strikes-Back.html",
        "imdb_url": "http://www.imdb.com/title/tt0080684"
    },
    {
        "genre": "Action, Adventure, Fantasy, Sci-Fi",
        "imdb_key": "tt0086190",
        "name": "Star Wars: Episode VI - Return of the Jedi",
        "year": "1983",
        "script_url": "http://www.imsdb.com/scripts/Star-Wars-Return-of-the-Jedi.html",
        "imdb_url": "http://www.imdb.com/title/tt0086190"
    },
    {
        "genre": "Action, Adventure, Fantasy, Sci-Fi",
        "imdb_key": "tt1104001",
        "name": "TRON: Legacy",
        "year": "2010",
        "script_url": "http://www.imsdb.com/scripts/TRON-Legacy.html",
        "imdb_url": "http://www.imdb.com/title/tt1104001"
    },
    {
        "genre": "Crime, Drama",
        "imdb_key": "tt0075314",
        "name": "Taxi Driver",
        "year": "1976",
        "script_url": "http://www.imsdb.com/scripts/Taxi-Driver.html",
        "imdb_url": "http://www.imdb.com/title/tt0075314"
    },
    {
        "genre": "Comedy, Fantasy",
        "imdb_key": "tt1637725",
        "name": "Ted",
        "year": "2012",
        "script_url": "http://www.imsdb.com/scripts/Ted.html",
        "imdb_url": "http://www.imdb.com/title/tt1637725"
    },
    {
        "genre": "Action, Sci-Fi",
        "imdb_key": "tt0103064",
        "name": "Terminator 2: Judgment Day",
        "year": "1991",
        "script_url": "http://www.imsdb.com/scripts/Terminator-2-Judgement-Day.html",
        "imdb_url": "http://www.imdb.com/title/tt0103064"
    },
    {
        "genre": "Romance, Sci-Fi, Thriller",
        "imdb_key": "tt1385826",
        "name": "The Adjustment Bureau",
        "year": "2011",
        "script_url": "http://www.imsdb.com/scripts/Adjustment-Bureau,-The.html",
        "imdb_url": "http://www.imdb.com/title/tt1385826"
    },
    {
        "genre": "Comedy, Crime",
        "imdb_key": "tt0118715",
        "name": "The Big Lebowski",
        "year": "1998",
        "script_url": "http://www.imsdb.com/scripts/Big-Lebowski,-The.html",
        "imdb_url": "http://www.imdb.com/title/tt0118715"
    },
    {
        "genre": "Action, Mystery, Thriller",
        "imdb_key": "tt0258463",
        "name": "The Bourne Identity",
        "year": "2002",
        "script_url": "http://www.imsdb.com/scripts/Bourne-Identity,-The.html",
        "imdb_url": "http://www.imdb.com/title/tt0258463"
    },
    {
        "genre": "Action, Thriller",
        "imdb_key": "tt0440963",
        "name": "The Bourne Ultimatum",
        "year": "2007",
        "script_url": "http://www.imsdb.com/scripts/Bourne-Ultimatum,-The.html",
        "imdb_url": "http://www.imdb.com/title/tt0440963"
    },
    {
        "genre": "Sci-Fi, Thriller",
        "imdb_key": "tt0289879",
        "name": "The Butterfly Effect",
        "year": "2004",
        "script_url": "http://www.imsdb.com/scripts/Butterfly-Effect,-The.html",
        "imdb_url": "http://www.imdb.com/title/tt0289879"
    },
    {
        "genre": "Adventure, Family, Fantasy",
        "imdb_key": "tt0363771",
        "name": "The Chronicles of Narnia: The Lion, the Witch and the Wardrobe",
        "year": "2005",
        "script_url": "http://www.imsdb.com/scripts/Chronicles-of-Narnia-The-Lion,-the-Witch-and-the-Wardrobe.html",
        "imdb_url": "http://www.imdb.com/title/tt0363771"
    },
    {
        "genre": "Drama, Fantasy, Romance",
        "imdb_key": "tt0421715",
        "name": "The Curious Case of Benjamin Button",
        "year": "2008",
        "script_url": "http://www.imsdb.com/scripts/Curious-Case-of-Benjamin-Button,-The.html",
        "imdb_url": "http://www.imdb.com/title/tt0421715"
    },
    {
        "genre": "Action, Thriller",
        "imdb_key": "tt1345836",
        "name": "The Dark Knight Rises",
        "year": "2012",
        "script_url": "http://www.imsdb.com/scripts/Dark-Knight-Rises,-The.html",
        "imdb_url": "http://www.imdb.com/title/tt1345836"
    },
    {
        "genre": "Drama, Sci-Fi, Thriller",
        "imdb_key": "tt0970416",
        "name": "The Day the Earth Stood Still",
        "year": "2008",
        "script_url": "http://www.imsdb.com/scripts/Day-the-Earth-Stood-Still,-The.html",
        "imdb_url": "http://www.imdb.com/title/tt0970416"
    },
    {
        "genre": "Drama, Mystery, Thriller",
        "imdb_key": "tt0118971",
        "name": "The Devil's Advocate",
        "year": "1997",
        "script_url": "http://www.imsdb.com/scripts/Devil's-Advocate.html",
        "imdb_url": "http://www.imdb.com/title/tt0118971"
    },
    {
        "genre": "Comedy, Drama, Fantasy, Romance",
        "imdb_key": "tt0218967",
        "name": "The Family Man",
        "year": "2000",
        "script_url": "http://www.imsdb.com/scripts/Family-Man,-The.html",
        "imdb_url": "http://www.imdb.com/title/tt0218967"
    },
    {
        "genre": "Crime, Drama, Mystery, Thriller",
        "imdb_key": "tt1568346",
        "name": "The Girl with the Dragon Tattoo",
        "year": "2011",
        "script_url": "http://www.imsdb.com/scripts/Girl-with-the-Dragon-Tattoo,-The.html",
        "imdb_url": "http://www.imdb.com/title/tt1568346"
    },
    {
        "genre": "Crime, Drama",
        "imdb_key": "tt0068646",
        "name": "The Godfather",
        "year": "1972",
        "script_url": "http://www.imsdb.com/scripts/Godfather.html",
        "imdb_url": "http://www.imdb.com/title/tt0068646"
    },
    {
        "genre": "Crime, Drama",
        "imdb_key": "tt0071562",
        "name": "The Godfather: Part II",
        "year": "1974",
        "script_url": "http://www.imsdb.com/scripts/Godfather-Part-II.html",
        "imdb_url": "http://www.imdb.com/title/tt0071562"
    },
    {
        "genre": "Crime, Drama",
        "imdb_key": "tt0099674",
        "name": "The Godfather: Part III",
        "year": "1990",
        "script_url": "http://www.imsdb.com/scripts/Godfather-Part-III,-The.html",
        "imdb_url": "http://www.imdb.com/title/tt0099674"
    },
    {
        "genre": "Comedy, Drama, Romance",
        "imdb_key": "tt0061722",
        "name": "The Graduate",
        "year": "1967",
        "script_url": "http://www.imsdb.com/scripts/Graduate,-The.html",
        "imdb_url": "http://www.imdb.com/title/tt0061722"
    },
    {
        "genre": "Crime, Drama, Fantasy, Mystery",
        "imdb_key": "tt0120689",
        "name": "The Green Mile",
        "year": "1999",
        "script_url": "http://www.imsdb.com/scripts/Green-Mile,-The.html",
        "imdb_url": "http://www.imdb.com/title/tt0120689"
    },
    {
        "genre": "Drama",
        "imdb_key": "tt1454029",
        "name": "The Help",
        "year": "2011",
        "script_url": "http://www.imsdb.com/scripts/Help,-The.html",
        "imdb_url": "http://www.imdb.com/title/tt1454029"
    },
    {
        "genre": "Biography, Drama, Thriller",
        "imdb_key": "tt0140352",
        "name": "The Insider",
        "year": "1999",
        "script_url": "http://www.imsdb.com/scripts/Insider,-The.html",
        "imdb_url": "http://www.imdb.com/title/tt0140352"
    },
    {
        "genre": "Comedy, Fantasy",
        "imdb_key": "tt1058017",
        "name": "The Invention of Lying",
        "year": "2009",
        "script_url": "http://www.imsdb.com/scripts/Invention-of-Lying,-The.html",
        "imdb_url": "http://www.imdb.com/title/tt1058017"
    },
    {
        "genre": "Biography, Drama, History",
        "imdb_key": "tt1504320",
        "name": "The King's Speech",
        "year": "2010",
        "script_url": "http://www.imsdb.com/scripts/King's-Speech,-The.html",
        "imdb_url": "http://www.imdb.com/title/tt1504320"
    },
    {
        "genre": "Crime, Drama, Thriller",
        "imdb_key": "tt1189340",
        "name": "The Lincoln Lawyer",
        "year": "2011",
        "script_url": "http://www.imsdb.com/scripts/Lincoln-Lawyer,-The.html",
        "imdb_url": "http://www.imdb.com/title/tt1189340"
    },
    {
        "genre": "Adventure, Fantasy",
        "imdb_key": "tt0120737",
        "name": "The Lord of the Rings: The Fellowship of the Ring",
        "year": "2001",
        "script_url": "http://www.imsdb.com/scripts/Lord-of-the-Rings-Fellowship-of-the-Ring,-The.html",
        "imdb_url": "http://www.imdb.com/title/tt0120737"
    },
    {
        "genre": "Adventure, Fantasy",
        "imdb_key": "tt0167260",
        "name": "The Lord of the Rings: The Return of the King",
        "year": "2003",
        "script_url": "http://www.imsdb.com/scripts/Lord-of-the-Rings-Return-of-the-King.html",
        "imdb_url": "http://www.imdb.com/title/tt0167260"
    },
    {
        "genre": "Adventure, Fantasy",
        "imdb_key": "tt0167261",
        "name": "The Lord of the Rings: The Two Towers",
        "year": "2002",
        "script_url": "http://www.imsdb.com/scripts/Lord-of-the-Rings-The-Two-Towers.html",
        "imdb_url": "http://www.imdb.com/title/tt0167261"
    },
    {
        "genre": "Action, Adventure, Sci-Fi",
        "imdb_key": "tt0119567",
        "name": "The Lost World: Jurassic Park",
        "year": "1997",
        "script_url": "http://www.imsdb.com/scripts/Jurassic-Park-The-Lost-World.html",
        "imdb_url": "http://www.imdb.com/title/tt0119567"
    },
    {
        "genre": "Action, Sci-Fi",
        "imdb_key": "tt0133093",
        "name": "The Matrix",
        "year": "1999",
        "script_url": "http://www.imsdb.com/scripts/Matrix,-The.html",
        "imdb_url": "http://www.imdb.com/title/tt0133093"
    },
    {
        "genre": "Action, Sci-Fi",
        "imdb_key": "tt0234215",
        "name": "The Matrix Reloaded",
        "year": "2003",
        "script_url": "http://www.imsdb.com/scripts/Matrix-Reloaded,-The.html",
        "imdb_url": "http://www.imdb.com/title/tt0234215"
    },
    {
        "genre": "Drama, Romance",
        "imdb_key": "tt1659337",
        "name": "The Perks of Being a Wallflower",
        "year": "2012",
        "script_url": "http://www.imsdb.com/scripts/Perks-of-Being-a-Wallflower,-The.html",
        "imdb_url": "http://www.imdb.com/title/tt1659337"
    },
    {
        "genre": "Adventure, Drama",
        "imdb_key": "tt0898367",
        "name": "The Road",
        "year": "2009",
        "script_url": "http://www.imsdb.com/scripts/Road,-The.html",
        "imdb_url": "http://www.imdb.com/title/tt0898367"
    },
    {
        "genre": "Crime, Drama",
        "imdb_key": "tt0111161",
        "name": "The Shawshank Redemption",
        "year": "1994",
        "script_url": "http://www.imsdb.com/scripts/Shawshank-Redemption,-The.html",
        "imdb_url": "http://www.imdb.com/title/tt0111161"
    },
    {
        "genre": "Drama, Mystery, Thriller",
        "imdb_key": "tt0167404",
        "name": "The Sixth Sense",
        "year": "1999",
        "script_url": "http://www.imsdb.com/scripts/Sixth-Sense,-The.html",
        "imdb_url": "http://www.imdb.com/title/tt0167404"
    },
    {
        "genre": "Biography, Drama",
        "imdb_key": "tt1285016",
        "name": "The Social Network",
        "year": "2010",
        "script_url": "http://www.imsdb.com/scripts/Social-Network,-The.html",
        "imdb_url": "http://www.imdb.com/title/tt1285016"
    },
    {
        "genre": "Drama",
        "imdb_key": "tt0120382",
        "name": "The Truman Show",
        "year": "1998",
        "script_url": "http://www.imsdb.com/scripts/Truman-Show,-The.html",
        "imdb_url": "http://www.imdb.com/title/tt0120382"
    },
    {
        "genre": "Comedy, Romance",
        "imdb_key": "tt1142988",
        "name": "The Ugly Truth",
        "year": "2009",
        "script_url": "http://www.imsdb.com/scripts/Ugly-Truth,-The.html",
        "imdb_url": "http://www.imdb.com/title/tt1142988"
    },
    {
        "genre": "Crime, Drama, Thriller",
        "imdb_key": "tt0114814",
        "name": "The Usual Suspects",
        "year": "1995",
        "script_url": "http://www.imsdb.com/scripts/Usual-Suspects,-The.html",
        "imdb_url": "http://www.imdb.com/title/tt0114814"
    },
    {
        "genre": "Biography, Comedy, Crime, Drama",
        "imdb_key": "tt0993846",
        "name": "The Wolf of Wall Street",
        "year": "2013",
        "script_url": "http://www.imsdb.com/scripts/Wolf-of-Wall-Street,-The.html",
        "imdb_url": "http://www.imdb.com/title/tt0993846"
    },
    {
        "genre": "Comedy, Romance",
        "imdb_key": "tt0129387",
        "name": "There's Something About Mary",
        "year": "1998",
        "script_url": "http://www.imsdb.com/scripts/There's-Something-About-Mary.html",
        "imdb_url": "http://www.imdb.com/title/tt0129387"
    },
    {
        "genre": "Action, Adventure, Fantasy",
        "imdb_key": "tt0800369",
        "name": "Thor",
        "year": "2011",
        "script_url": "http://www.imsdb.com/scripts/Thor.html",
        "imdb_url": "http://www.imdb.com/title/tt0800369"
    },
    {
        "genre": "Drama, Romance",
        "imdb_key": "tt0120338",
        "name": "Titanic",
        "year": "1997",
        "script_url": "http://www.imsdb.com/scripts/Titanic.html",
        "imdb_url": "http://www.imdb.com/title/tt0120338"
    },
    {
        "genre": "Animation, Adventure, Comedy, Family, Fantasy",
        "imdb_key": "tt0114709",
        "name": "Toy Story",
        "year": "1995",
        "script_url": "http://www.imsdb.com/scripts/Toy-Story.html",
        "imdb_url": "http://www.imdb.com/title/tt0114709"
    },
    {
        "genre": "Crime, Drama, Thriller",
        "imdb_key": "tt0108399",
        "name": "True Romance",
        "year": "1993",
        "script_url": "http://www.imsdb.com/scripts/True-Romance.html",
        "imdb_url": "http://www.imdb.com/title/tt0108399"
    },
    {
        "genre": "Drama, Fantasy, Romance",
        "imdb_key": "tt1099212",
        "name": "Twilight",
        "year": "2008",
        "script_url": "http://www.imsdb.com/scripts/Twilight.html",
        "imdb_url": "http://www.imdb.com/title/tt1099212"
    },
    {
        "genre": "Comedy",
        "imdb_key": "tt0096320",
        "name": "Twins",
        "year": "1988",
        "script_url": "http://www.imsdb.com/scripts/Twins.html",
        "imdb_url": "http://www.imdb.com/title/tt0096320"
    },
    {
        "genre": "Action, Mystery, Thriller",
        "imdb_key": "tt1401152",
        "name": "Unknown",
        "year": "2011",
        "script_url": "http://www.imsdb.com/scripts/Unknown.html",
        "imdb_url": "http://www.imdb.com/title/tt1401152"
    },
    {
        "genre": "Drama, Romance",
        "imdb_key": "tt1193138",
        "name": "Up in the Air",
        "year": "2009",
        "script_url": "http://www.imsdb.com/scripts/Up-in-the-Air.html",
        "imdb_url": "http://www.imdb.com/title/tt1193138"
    },
    {
        "genre": "Animation, Adventure, Family, Sci-Fi",
        "imdb_key": "tt0910970",
        "name": "WALL-E",
        "year": "2008",
        "script_url": "http://www.imsdb.com/scripts/Wall-E.html",
        "imdb_url": "http://www.imdb.com/title/tt0910970"
    },
    {
        "genre": "Action, Crime, Fantasy, Thriller",
        "imdb_key": "tt0493464",
        "name": "Wanted",
        "year": "2008",
        "script_url": "http://www.imsdb.com/scripts/Wanted.html",
        "imdb_url": "http://www.imdb.com/title/tt0493464"
    },
    {
        "genre": "Crime, Drama, Mystery, Thriller",
        "imdb_key": "tt0120890",
        "name": "Wild Things",
        "year": "1998",
        "script_url": "http://www.imsdb.com/scripts/Wild-Things.html",
        "imdb_url": "http://www.imdb.com/title/tt0120890"
    },
    {
        "genre": "Action, Adventure, Drama, Fantasy, Romance",
        "imdb_key": "tt0096446",
        "name": "Willow",
        "year": "1988",
        "script_url": "http://www.imsdb.com/scripts/Willow.html",
        "imdb_url": "http://www.imdb.com/title/tt0096446"
    },
    {
        "genre": "Action, Adventure, Sci-Fi",
        "imdb_key": "tt0120903",
        "name": "X-Men",
        "year": "2000",
        "script_url": "http://www.imsdb.com/scripts/X-Men.html",
        "imdb_url": "http://www.imdb.com/title/tt0120903"
    },
    {
        "genre": "Action, Adventure, Sci-Fi, Thriller",
        "imdb_key": "tt0458525",
        "name": "X-Men Origins: Wolverine",
        "year": "2009",
        "script_url": "http://www.imsdb.com/scripts/X-Men-Origins-Wolverine.html",
        "imdb_url": "http://www.imdb.com/title/tt0458525"
    },
    {
        "genre": "Comedy, Romance",
        "imdb_key": "tt1068680",
        "name": "Yes Man",
        "year": "2008",
        "script_url": "http://www.imsdb.com/scripts/Yes-Man.html",
        "imdb_url": "http://www.imdb.com/title/tt1068680"
    },
    {
        "genre": "Drama, History, Thriller",
        "imdb_key": "tt1790885",
        "name": "Zero Dark Thirty",
        "year": "2012",
        "script_url": "http://www.imsdb.com/scripts/Zero-Dark-Thirty.html",
        "imdb_url": "http://www.imdb.com/title/tt1790885"
    }
]
